counter_threebit/adder_onebit.sv
module adder_onebit (
	input logic A,
	input logic  B,
	input logic  CIN,
	output logic  S,
	output logic  COUT
	);
	
	assign S = (A ^ B) ^ CIN;
	assign COUT = (A & B) | (CIN & (A ^ B));

endmodule : adder_onebit

counter_threebit/adder_onebit_tb.sv
`timescale 1ns/1ps
`include "adder_onebit.sv"

module adder_onebit_tb;
logic a, b, cin;
logic s, cout;

adder_onebit dut (.S (s), .COUT (cout), .A (a), .B (b), .CIN (cin)); // Instantiation of circuit to be tested

initial begin // Stimulus generator
$dumpfile("adder_onebit_tb.vcd");
$dumpvars(0, adder_onebit_tb);

a = 0; b = 0; cin= 0;
#10; a = 1; b = 0; cin = 0;
#10; a = 0; b = 1; cin = 0;
#10; a = 1; b = 1; cin = 0;
#10; a = 0; b = 0; cin = 1;
#10; a = 1; b = 0; cin = 1;
#10; a = 0; b = 1; cin = 1;
#10; a = 1; b = 1; cin = 1;
#10;
// Add further test inputs here.

end

initial begin // Response monitor

$monitor("t = %3d a = %d b = %d cin = %d cout = %d s = %d", $time, a, b, cin, cout, s);

end

endmodule
// End of testbench code for adder_1bit.v module

counter_threebit/adder_onebit_tb.vcd
$date
	Tue Mar 15 21:58:54 2022
$end
$version
	Icarus Verilog
$end
$timescale
	1ps
$end
$scope module adder_onebit_tb $end
$var wire 1 ! s $end
$var wire 1 " cout $end
$var reg 1 # a $end
$var reg 1 $ b $end
$var reg 1 % cin $end
$scope module dut $end
$var wire 1 # A $end
$var wire 1 $ B $end
$var wire 1 % CIN $end
$var wire 1 " COUT $end
$var wire 1 ! S $end
$upscope $end
$upscope $end
$enddefinitions $end
#0
$dumpvars
0%
0$
0#
0"
0!
$end
#10000
1!
1#
#20000
1$
0#
#30000
0!
1"
1#
#40000
0"
1!
1%
0$
0#
#50000
1"
0!
1#
#60000
1$
0#
#70000
1!
1#
