counter_threebit/adder_onebit.sv
module adder_onebit (
	input logic A,
	input logic  B,
	input logic  CIN,
	output logic  S,
	output logic  COUT
	);
	
	assign S = (A ^ B) ^ CIN;
	assign COUT = (A & B) | (CIN & (A ^ B));

endmodule : adder_onebit

counter_threebit/adder_threebit.sv
`include "adder_onebit.sv"

module adder_threebit(
	input logic [2:0] A,
	input logic [2:0] B,
	output logic [2:0] S,
	output logic COUT
	);
	
	logic C1, C2;
	
	adder_onebit A1 (A[0], B[0], 1'b0, S[0], C1);
	adder_onebit A2 (A[1], B[1], C1, S[1], C2);
	adder_onebit A3 (A[2], B[2], C2, S[2], COUT);

endmodule : adder_threebit

counter_threebit/adder_threebit_tb.sv
// Start of testbench code to test adder_3bit.v module
`timescale 1ns/1ps
`include "adder_threebit.sv"

module adder_threebit_tb;
logic [2:0] a, b, s;
logic cout;

adder_threebit  dut (a, b, s, cout);

initial begin // Stimulus generator
$dumpfile("adder_threebit_tb.vcd");
$dumpvars(0, adder_threebit_tb);

a = 3'h0;
b = 3'h0;

#20; a = 3'h1; b=3'h1; // Expect 2
#20; a = 3'h2; b=3'h2; // Expect 4
#20; a = 3'h4; b=3'h1; // Expect 5
#20; a = 3'h4; b=3'h3; // Expect 7
#20; a = 3'h4; b=3'h4; //Expect 8 (cout = 1, the rest 000)
#20; a = 3'h7; b=3'h7; //Expect 14 (cout = 1, the rest 110)
#20; a = 3'h0; b=3'h0; //Expect 14 (cout = 1, the rest 110)
// Add further test inputs here.

end

initial begin // Response monitor

$monitor("t=%3d a2=%d a1=%d a0=%d b2=%d b1=%d b0=%d cout=%d s2=%d s1=%d s0=%d", $time, a[2], a[1], a[0], b[2], b[1], b[0], cout, s[2], s[2], s[0]);

end

endmodule
// End of testbench code for adder_3bit.v module

counter_threebit/adder_threebit_tb.vcd
$date
	Wed Mar 16 18:51:49 2022
$end
$version
	Icarus Verilog
$end
$timescale
	1ps
$end
$scope module adder_threebit_tb $end
$var wire 3 ! s [2:0] $end
$var wire 1 " cout $end
$var reg 3 # a [2:0] $end
$var reg 3 $ b [2:0] $end
$scope module dut $end
$var wire 3 % A [2:0] $end
$var wire 3 & B [2:0] $end
$var wire 3 ' S [2:0] $end
$var wire 1 " COUT $end
$var wire 1 ( C2 $end
$var wire 1 ) C1 $end
$scope module A1 $end
$var wire 1 * A $end
$var wire 1 + B $end
$var wire 1 , CIN $end
$var wire 1 ) COUT $end
$var wire 1 - S $end
$upscope $end
$scope module A2 $end
$var wire 1 . A $end
$var wire 1 / B $end
$var wire 1 ) CIN $end
$var wire 1 ( COUT $end
$var wire 1 0 S $end
$upscope $end
$scope module A3 $end
$var wire 1 1 A $end
$var wire 1 2 B $end
$var wire 1 ( CIN $end
$var wire 1 " COUT $end
$var wire 1 3 S $end
$upscope $end
$upscope $end
$upscope $end
$enddefinitions $end
#0
$dumpvars
03
02
01
00
0/
0.
0-
0,
0+
0*
0)
0(
b0 '
b0 &
b0 %
b0 $
b0 #
0"
b0 !
$end
#20000
b10 !
b10 '
10
1)
1+
1*
b1 $
b1 &
b1 #
b1 %
#40000
00
b100 !
b100 '
13
0)
1(
0+
1/
0*
1.
b10 $
b10 &
b10 #
b10 %
#60000
0"
1-
0(
b101 !
b101 '
13
1+
0/
0.
11
b1 $
b1 &
b100 #
b100 %
#80000
b111 !
b111 '
10
1/
b11 $
b11 &
#100000
0-
00
b0 !
b0 '
03
1"
0+
0/
12
b100 $
b100 &
#120000
10
b110 !
b110 '
13
1)
1(
1+
1/
1*
1.
b111 $
b111 &
b111 #
b111 %
#140000
00
b0 !
b0 '
03
0)
0(
0"
0+
0/
02
0*
0.
01
b0 $
b0 &
b0 #
b0 %
