counter_threebit/d_ff_three.sv
module d_ff_three(
	input logic CLK,
	input logic [2:0] D,
	input logic CLRN, // async clear
	output logic [2:0] Q
	);
	
	always @(posedge CLK or negedge CLRN) begin
		if(CLRN == 0)
			Q <= 0;
		else
			Q <= D;
	end

endmodule : d_ff_three

counter_threebit/adder_onebit.sv
module adder_onebit (
	input logic A,
	input logic  B,
	input logic  CIN,
	output logic  S,
	output logic  COUT
	);
	
	assign S = (A ^ B) ^ CIN;
	assign COUT = (A & B) | (CIN & (A ^ B));

endmodule : adder_onebit

counter_threebit/adder_threebit.sv
`include "adder_onebit.sv"

module adder_threebit(
	input logic [2:0] A,
	input logic [2:0] B,
	output logic [2:0] S,
	output logic COUT
	);
	
	logic C1, C2;
	
	adder_onebit A1 (A[0], B[0], 1'b0, S[0], C1);
	adder_onebit A2 (A[1], B[1], C1, S[1], C2);
	adder_onebit A3 (A[2], B[2], C2, S[2], COUT);

endmodule : adder_threebit

counter_threebit/counter_threebit.sv
`include "adder_threebit.sv"
`include "d_ff_three.sv"

module counter_threebit (
	input logic [2:0] A,
	input logic CLK,
	input logic CLRN,
	output logic [2:0] F,
	output logic COUT
);

logic [2:0] D;

adder_threebit adder (A, F, D, COUT);
d_ff_three register (CLK, D, CLRN, F);

endmodule : counter_threebit

counter_threebit/counter_threebit_tb.sv
// Start of testbench code for counter_project
`timescale 1ns/1ps
`include "counter_threebit.sv"

module counter_threebit_tb;
logic clear, clk, cout;
logic [2:0] a, f;

counter_threebit dut(.CLRN (clear), .CLK (clk), .COUT (cout), .A(a), .F(f)); // Instantiation of circuit to be tested

initial begin // Stimulus generator
$dumpfile("counter_threebit_tb.vcd");
$dumpvars(0, counter_threebit_tb);

a = 3'h1;
clear = 1'b0;
clk = 1'b1;

// Testing add 1
#10; clear = 1;
#10; clk = 1;
#10; clk = 0; 
#10; clk = 1; 
#10; clk = 0;
#10; clk = 1;
#10; clk = 0; 
#10; clk = 1; 
#10; clk = 0;
#10; clk = 1;
#10; clk = 0; 
#10; clk = 1; 
#10; clk = 0;
#10; clk = 1;
#10; clk = 0;
#10; clk = 1;
#10; clk = 0;
#10; clk = 1;
#10; clear = 0;
#10; clear = 1;

// Testing add 4
a = 3'h4;
#10; clear = 1;
#10; clk = 1;
#10; clk = 0; 
#10; clk = 1; 
#10; clk = 0;
#10; clk = 1;
#10; clk = 0;
#10; clk = 1;
#10; clear = 0;
#10; clear = 1;

end

initial begin // Response monitor

$monitor("t=%3d clk=%d clear=%d a2=%d a1=%d a0=%d f2=%d f1=%d f0=%d cout=%d", $time, clk, clear, a[2], a[1], a[0], f[2], f[1], f[0], cout);

end

endmodule
// End of testbench code for counter_3bit_v module

counter_threebit/counter_threebit_tb.vcd
$date
	Wed Mar 16 19:14:21 2022
$end
$version
	Icarus Verilog
$end
$timescale
	1ps
$end
$scope module counter_threebit_tb $end
$var wire 3 ! f [2:0] $end
$var wire 1 " cout $end
$var reg 3 # a [2:0] $end
$var reg 1 $ clear $end
$var reg 1 % clk $end
$scope module dut $end
$var wire 3 & A [2:0] $end
$var wire 1 % CLK $end
$var wire 1 $ CLRN $end
$var wire 3 ' F [2:0] $end
$var wire 3 ( D [2:0] $end
$var wire 1 " COUT $end
$scope module adder $end
$var wire 3 ) A [2:0] $end
$var wire 3 * S [2:0] $end
$var wire 1 " COUT $end
$var wire 1 + C2 $end
$var wire 1 , C1 $end
$var wire 3 - B [2:0] $end
$scope module A1 $end
$var wire 1 . A $end
$var wire 1 / B $end
$var wire 1 0 CIN $end
$var wire 1 , COUT $end
$var wire 1 1 S $end
$upscope $end
$scope module A2 $end
$var wire 1 2 A $end
$var wire 1 3 B $end
$var wire 1 , CIN $end
$var wire 1 + COUT $end
$var wire 1 4 S $end
$upscope $end
$scope module A3 $end
$var wire 1 5 A $end
$var wire 1 6 B $end
$var wire 1 + CIN $end
$var wire 1 " COUT $end
$var wire 1 7 S $end
$upscope $end
$upscope $end
$scope module register $end
$var wire 1 % CLK $end
$var wire 1 $ CLRN $end
$var wire 3 8 D [2:0] $end
$var reg 3 9 Q [2:0] $end
$upscope $end
$upscope $end
$upscope $end
$enddefinitions $end
#0
$dumpvars
b0 9
b1 8
07
06
05
04
03
02
11
00
0/
1.
b0 -
0,
0+
b1 *
b1 )
b1 (
b0 '
b1 &
1%
0$
b1 #
0"
b0 !
$end
#10000
1$
#30000
0%
#40000
14
b10 (
b10 *
b10 8
01
1,
1/
b1 !
b1 '
b1 -
b1 9
1%
#50000
0%
#60000
b11 (
b11 *
b11 8
11
0,
13
0/
b10 !
b10 '
b10 -
b10 9
1%
#70000
0%
#80000
17
1+
04
b100 (
b100 *
b100 8
01
1,
1/
b11 !
b11 '
b11 -
b11 9
1%
#90000
0%
#100000
0"
0+
17
b101 (
b101 *
b101 8
11
0,
16
03
0/
b100 !
b100 '
b100 -
b100 9
1%
#110000
0%
#120000
14
b110 (
b110 *
b110 8
01
1,
1/
b101 !
b101 '
b101 -
b101 9
1%
#130000
0%
#140000
b111 (
b111 *
b111 8
11
0,
13
0/
b110 !
b110 '
b110 -
b110 9
1%
#150000
0%
#160000
1"
07
1+
04
b0 (
b0 *
b0 8
01
1,
1/
b111 !
b111 '
b111 -
b111 9
1%
#170000
0%
#180000
0"
0+
07
b1 (
b1 *
b1 8
11
0,
06
03
0/
b0 !
b0 '
b0 -
b0 9
1%
#190000
0$
#200000
01
b100 (
b100 *
b100 8
17
0.
15
b100 #
b100 &
b100 )
1$
#230000
0%
#240000
b0 (
b0 *
b0 8
07
1"
16
b100 !
b100 '
b100 -
b100 9
1%
#250000
0%
#260000
b100 (
b100 *
b100 8
17
0"
06
b0 !
b0 '
b0 -
b0 9
1%
#270000
0%
#280000
b0 (
b0 *
b0 8
07
1"
16
b100 !
b100 '
b100 -
b100 9
1%
#290000
b100 (
b100 *
b100 8
17
0"
06
b0 !
b0 '
b0 -
b0 9
0$
#300000
1$
