n_bit_counter/n_bit_counter.sv
module n_bit_adder #(
	parameter WIDTH = 3
)(
	input wire [WIDTH - 1:0] A,
	input wire [WIDTH - 1:0] B,
	output wire [WIDTH - 1:0] S,
	output wire COUT
);
	
	wire [WIDTH:0] D = A + B;
	
	assign S = D[WIDTH - 1:0];
	assign COUT = D[WIDTH];

endmodule : n_bit_adder

module n_d_ff #(
	parameter WIDTH = 3
)(
	input logic CLK,
	input logic [WIDTH - 1:0] D,
	input logic CLRN, // async clear
	output logic [WIDTH - 1:0] Q
);

	// Store from D on clock, CLRN is async
	always @(posedge CLK or negedge CLRN) begin
		if(CLRN == 0)
			Q <= 0;
		else
			Q <= D;
	end

endmodule : n_d_ff

module n_bit_counter #(
	parameter WIDTH = 3
)(
	input logic [WIDTH - 1:0] A,
	input logic CLK,
	input logic CLRN,
	output logic [WIDTH - 1:0]F,
	output logic COUT
);

	logic [WIDTH - 1:0] D;
	
	n_bit_adder adder(A, F, D, COUT);
	
	n_d_ff register(CLK, D, CLRN, F);

endmodule : n_bit_counter

n_bit_counter/n_bit_counter_tb.sv
// Start of testbench code for counter_project
`timescale 1ns/1ps
`include "n_bit_counter.sv"
module n_bit_counter_tb;
logic clear, clk, cout;
logic [2:0] a, f;

n_bit_counter #(3) dut(.CLRN (clear), .CLK (clk), .COUT (cout), .A(a), .F(f)); // Instantiation of circuit to be tested

initial begin // Stimulus generator
$dumpfile("n_bit_counter_tb.vcd");
$dumpvars(0, n_bit_counter_tb);

a = 3'h1;
clear = 1'b0;
clk = 1'b1;

// Testing add 1
#10; clear = 1;
#10; clk = 1;
#10; clk = 0; 
#10; clk = 1; 
#10; clk = 0;
#10; clk = 1;
#10; clk = 0; 
#10; clk = 1; 
#10; clk = 0;
#10; clk = 1;
#10; clk = 0; 
#10; clk = 1; 
#10; clk = 0;
#10; clk = 1;
#10; clk = 0;
#10; clk = 1;
#10; clk = 0;
#10; clk = 1;
#10; clear = 0;
#10; clear = 1;

// Testing add 4
a = 3'h4;
#10; clear = 1;
#10; clk = 1;
#10; clk = 0; 
#10; clk = 1; 
#10; clk = 0;
#10; clk = 1;
#10; clk = 0;
#10; clk = 1;
#10; clear = 0;
#10; clear = 1;


// Add further test inputs.

end

initial begin // Response monitor

$monitor("t=%3d clk=%d clear=%d a2=%d a1=%d a0=%d f2=%d f1=%d f0=%d cout=%d", $time, clk, clear, a[2], a[1], a[0], f[2], f[1], f[0], cout);

end

endmodule
// End of testbench code for counter_3bit_v module

n_bit_counter/n_bit_counter_tb.vcd
$date
	Wed Mar 16 19:28:49 2022
$end
$version
	Icarus Verilog
$end
$timescale
	1ps
$end
$scope module n_bit_counter_tb $end
$var wire 3 ! f [2:0] $end
$var wire 1 " cout $end
$var reg 3 # a [2:0] $end
$var reg 1 $ clear $end
$var reg 1 % clk $end
$scope module dut $end
$var wire 3 & A [2:0] $end
$var wire 1 % CLK $end
$var wire 1 $ CLRN $end
$var wire 3 ' F [2:0] $end
$var wire 3 ( D [2:0] $end
$var wire 1 " COUT $end
$scope module adder $end
$var wire 3 ) A [2:0] $end
$var wire 3 * S [2:0] $end
$var wire 4 + D [3:0] $end
$var wire 1 " COUT $end
$var wire 3 , B [2:0] $end
$upscope $end
$scope module register $end
$var wire 1 % CLK $end
$var wire 1 $ CLRN $end
$var wire 3 - D [2:0] $end
$var reg 3 . Q [2:0] $end
$upscope $end
$upscope $end
$upscope $end
$enddefinitions $end
#0
$dumpvars
b0 .
b1 -
b0 ,
b1 +
b1 *
b1 )
b1 (
b0 '
b1 &
1%
0$
b1 #
0"
b0 !
$end
#10000
1$
#30000
0%
#40000
b10 (
b10 *
b10 -
b10 +
b1 !
b1 '
b1 ,
b1 .
1%
#50000
0%
#60000
b11 (
b11 *
b11 -
b11 +
b10 !
b10 '
b10 ,
b10 .
1%
#70000
0%
#80000
b100 (
b100 *
b100 -
b100 +
b11 !
b11 '
b11 ,
b11 .
1%
#90000
0%
#100000
b101 (
b101 *
b101 -
b101 +
b100 !
b100 '
b100 ,
b100 .
1%
#110000
0%
#120000
b110 (
b110 *
b110 -
b110 +
b101 !
b101 '
b101 ,
b101 .
1%
#130000
0%
#140000
b111 (
b111 *
b111 -
b111 +
b110 !
b110 '
b110 ,
b110 .
1%
#150000
0%
#160000
b0 (
b0 *
b0 -
1"
b1000 +
b111 !
b111 '
b111 ,
b111 .
1%
#170000
0%
#180000
b1 (
b1 *
b1 -
0"
b1 +
b0 !
b0 '
b0 ,
b0 .
1%
#190000
0$
#200000
b100 (
b100 *
b100 -
b100 +
b100 #
b100 &
b100 )
1$
#230000
0%
#240000
b0 (
b0 *
b0 -
1"
b1000 +
b100 !
b100 '
b100 ,
b100 .
1%
#250000
0%
#260000
b100 (
b100 *
b100 -
0"
b100 +
b0 !
b0 '
b0 ,
b0 .
1%
#270000
0%
#280000
b0 (
b0 *
b0 -
1"
b1000 +
b100 !
b100 '
b100 ,
b100 .
1%
#290000
b100 (
b100 *
b100 -
0"
b100 +
b0 !
b0 '
b0 ,
b0 .
0$
#300000
1$
